setup.cfg
setup.py
lab3/DeserializerJson.py
lab3/DeserializerYaml.py
lab3/Json.py
lab3/SerializerFactory.py
lab3/SerializerJson.py
lab3/SerializerYaml.py
lab3/Toml.py
lab3/Yaml.py
lab3/__init__.py
lab3/constants.py
lab3/tst.py
scserializer.egg-info/PKG-INFO
scserializer.egg-info/SOURCES.txt
scserializer.egg-info/dependency_links.txt
scserializer.egg-info/requires.txt
scserializer.egg-info/top_level.txt