Metadata-Version: 2.1
Name: scserializer
Version: 2.0.1
Summary: serializer of few formats
Author: Alexandra
Author-email: aleksa1012016@gmail.com
